{
    "usuarios": [
        {
            "usuario": "tuk684",
            "contrasena": "s3a3b7",
            "correo": "aalejo0@godaddy.com"
        },
        {
            "usuario": "zdd780",
            "contrasena": "m0r1i4",
            "correo": "rreina1@sun.com"
        },
        {
            "usuario": "ooo114",
            "contrasena": "w4c4m3",
            "correo": "kspurret2@huffingtonpost.com"
        },
        {
            "usuario": "rmc112",
            "contrasena": "w6k1t8",
            "correo": "hbambra3@tumblr.com"
        },
        {
            "usuario": "hkx470",
            "contrasena": "e0g3r9",
            "correo": "dstickney4@reuters.com"
        },
        {
            "usuario": "bks425",
            "contrasena": "s9d2s2",
            "correo": "dpaish5@acquirethisname.com"
        },
        {
            "usuario": "kdm080",
            "contrasena": "w0y1n9",
            "correo": "tmagenny6@blogtalkradio.com"
        },
        {
            "usuario": "edi616",
            "contrasena": "s8k9p7",
            "correo": "ecartmell7@mayoclinic.com"
        },
        {
            "usuario": "jim608",
            "contrasena": "r7i7t3",
            "correo": "rgovenlock8@tamu.edu"
        },
        {
            "usuario": "bpp741",
            "contrasena": "r1r7s4",
            "correo": "hcaswall9@barnesandnoble.com"
        }
    ]
}